texcreator/__init__.py
texcreator/module.py
texcreator-0.4.0.dist-info/METADATA
texcreator-0.4.0.dist-info/WHEEL
texcreator-0.4.0.dist-info/RECORD
