Metadata-Version: 2.1
Name: texcreator
Version: 0.4.0
Summary: latex document creator
Author: Artem Kovalev
Author-email: artem@kovalev.cc
Requires-Python: >=3.10,<4.0
Classifier: Programming Language :: Python :: 3
Classifier: Programming Language :: Python :: 3.10
Classifier: Programming Language :: Python :: 3.11
Classifier: Programming Language :: Python :: 3.12
